sifflet-0.4.3.dist-info/licenses/LICENSE
sifflet_cli/__init__.py
sifflet_cli/cli.py
sifflet_cli/logger.py
sifflet_cli/code/__init__.py
sifflet_cli/code/commands.py
sifflet_cli/code/monitor/__init__.py
sifflet_cli/code/monitor/commands.py
sifflet_cli/code/workspace/__init__.py
sifflet_cli/code/workspace/commands.py
sifflet_cli/configure/__init__.py
sifflet_cli/configure/commands.py
sifflet_cli/ingest/__init__.py
sifflet_cli/ingest/commands.py
sifflet_cli/rules/__init__.py
sifflet_cli/rules/commands.py
sifflet_cli/rules/displayrules.py
sifflet_cli/status/__init__.py
sifflet_cli/status/commands.py
sifflet-0.4.3.dist-info/METADATA
sifflet-0.4.3.dist-info/WHEEL
sifflet-0.4.3.dist-info/entry_points.txt
sifflet-0.4.3.dist-info/top_level.txt
sifflet-0.4.3.dist-info/RECORD
