Metadata-Version: 2.4
Name: sifflet
Version: 0.4.3
Summary: Sifflet CLI
Home-page: https://www.siffletdata.com/
Author: Sifflet
Author-email: support@siffletdata.com
Classifier: Programming Language :: Python :: 3
Classifier: Operating System :: OS Independent
Requires-Python: >=3.7
License-File: LICENSE
Requires-Dist: sifflet-sdk==0.4.3
Requires-Dist: click>=8.0.0
Requires-Dist: click-option-group<0.5.8,>=0.5.6
Requires-Dist: click_aliases>=1.0.1
Requires-Dist: rich>=12.4.4
Dynamic: author
Dynamic: author-email
Dynamic: classifier
Dynamic: description
Dynamic: description-content-type
Dynamic: home-page
Dynamic: license-file
Dynamic: requires-dist
Dynamic: requires-python
Dynamic: summary
